cerebro/__init__.py
cerebro/brain_viewer_test.py
cerebro/cerebro_brain_utils.py
cerebro/cerebro_brain_viewer.py
cerebro/cerebro_types.py
cerebro/cerebro_utils.py
cerebro/cerebro_window.py
cerebro/renderer.py
cerebro/renderer_test.py
data/templates/HCP/dscalars/S1200.MyelinMap_BC_MSMAll.32k_fs_LR.dscalar.nii
data/templates/HCP/dscalars/S1200.SmoothedMyelinMap_BC_MSMAll.32k_fs_LR.dscalar.nii
data/templates/HCP/dscalars/S1200.corrThickness_MSMAll.32k_fs_LR.dscalar.nii
data/templates/HCP/dscalars/S1200.curvature_MSMAll.32k_fs_LR.dscalar.nii
data/templates/HCP/dscalars/S1200.sulc_MSMAll.32k_fs_LR.dscalar.nii
data/templates/HCP/dscalars/S1200.thickness_MSMAll.32k_fs_LR.dscalar.nii
data/templates/HCP/dscalars/hcp.gradients.dscalar.nii
data/templates/HCP/dscalars/ones.dscalar.nii
data/templates/HCP/surfaces/S1200.L.flat.32k_fs_LR.surf.gii
data/templates/HCP/surfaces/S1200.L.inflated_MSMAll.32k_fs_LR.surf.gii
data/templates/HCP/surfaces/S1200.L.midthickness_MSMAll.32k_fs_LR.surf.gii
data/templates/HCP/surfaces/S1200.L.midthickness_MSMAll_va.32k_fs_LR.shape.gii
data/templates/HCP/surfaces/S1200.L.pial_MSMAll.32k_fs_LR.surf.gii
data/templates/HCP/surfaces/S1200.L.sphere.32k_fs_LR.surf.gii
data/templates/HCP/surfaces/S1200.L.very_inflated_MSMAll.32k_fs_LR.surf.gii
data/templates/HCP/surfaces/S1200.L.white_MSMAll.32k_fs_LR.surf.gii
data/templates/HCP/surfaces/S1200.R.flat.32k_fs_LR.surf.gii
data/templates/HCP/surfaces/S1200.R.inflated_MSMAll.32k_fs_LR.surf.gii
data/templates/HCP/surfaces/S1200.R.midthickness_MSMAll.32k_fs_LR.surf.gii
data/templates/HCP/surfaces/S1200.R.midthickness_MSMAll_va.32k_fs_LR.shape.gii
data/templates/HCP/surfaces/S1200.R.pial_MSMAll.32k_fs_LR.surf.gii
data/templates/HCP/surfaces/S1200.R.sphere.32k_fs_LR.surf.gii
data/templates/HCP/surfaces/S1200.R.very_inflated_MSMAll.32k_fs_LR.surf.gii
data/templates/HCP/surfaces/S1200.R.white_MSMAll.32k_fs_LR.surf.gii
data/templates/MNI152/MNI152_T1_2mm_brain.nii.gz
Cerebro_Viewer-0.0.10.5.dist-info/LICENSE
Cerebro_Viewer-0.0.10.5.dist-info/METADATA
Cerebro_Viewer-0.0.10.5.dist-info/WHEEL
Cerebro_Viewer-0.0.10.5.dist-info/top_level.txt
Cerebro_Viewer-0.0.10.5.dist-info/RECORD
