Metadata-Version: 2.1
Name: Cerebro_Viewer
Version: 0.0.10.5
Summary: Cerebro Viewer - A pythonic 3D viewer to visualize and plot brains
Author-email: "Sina Mansour L." <sina.mansour.lakouraj@gmail.com>
Project-URL: Homepage, https://github.com/sina-mansour/Cerebro_Viewer
Project-URL: Documentations, https://cerebro-viewer.readthedocs.io
Project-URL: Bug Tracker, https://github.com/sina-mansour/Cerebro_Viewer/issues
Keywords: 3D,Brain Viewer
Classifier: Programming Language :: Python :: 3
Classifier: License :: OSI Approved :: MIT License
Classifier: Operating System :: OS Independent
Requires-Python: >=3.7
License-File: LICENSE
Requires-Dist: numpy >=1.19
Requires-Dist: matplotlib
Requires-Dist: scipy
Requires-Dist: nibabel
Requires-Dist: trimesh
Requires-Dist: Panda3D
Requires-Dist: scikit-image
